Metadata-Version: 1.0
Name: clickhouse-http-client
Version: 1.0.2
Summary: clickhouse http client, author liyuanjun
Home-page: https://github.com/tomoncle/clickhouse-http-client
Author: liyuanjun
Author-email: 1123431949@qq.com
License: MIT
Platform: UNKNOWN
